golden_data/__init__.py
golden_data/get_daily_data.py
golden_data/get_eastmoney_concept_boards.py
golden_data/get_eastmoney_concept_daily_data.py
golden_data/get_eastmoney_concept_data.py
golden_data/get_eastmoney_industry_boards.py
golden_data/get_eastmoney_industry_data.py
golden_data/get_etf_daily_data.py
golden_data/get_stock_today_data.py
golden_data/get_sw_industry.py
golden_data/get_sw_industry_data.py
golden_data/__pycache__/__init__.cpython-39.pyc
golden_data/__pycache__/__init__.py
golden_data-0.0.3.dist-info/LICENSE.txt
golden_data-0.0.3.dist-info/METADATA
golden_data-0.0.3.dist-info/WHEEL
golden_data-0.0.3.dist-info/top_level.txt
golden_data-0.0.3.dist-info/RECORD
